.coveragerc
.mailmap
.stestr.conf
AUTHORS
CONTRIBUTING.rst
ChangeLog
HACKING.rst
LICENSE
README.md
babel.cfg
requirements.txt
setup.cfg
setup.py
test-requirements.txt
tox.ini
doc/source/conf.py
doc/source/index.rst
doc/source/readme.rst
doc/source/admin/index.rst
doc/source/cli/index.rst
doc/source/configuration/index.rst
doc/source/contributor/contributing.rst
doc/source/contributor/index.rst
doc/source/install/common_configure.rst
doc/source/install/common_prerequisites.rst
doc/source/install/get_started.rst
doc/source/install/index.rst
doc/source/install/install-obs.rst
doc/source/install/install-rdo.rst
doc/source/install/install-ubuntu.rst
doc/source/install/install.rst
doc/source/install/next-steps.rst
doc/source/install/verify.rst
doc/source/library/index.rst
doc/source/reference/index.rst
doc/source/user/index.rst
releasenotes/notes/.placeholder
releasenotes/source/conf.py
releasenotes/source/index.rst
releasenotes/source/unreleased.rst
releasenotes/source/_static/.placeholder
releasenotes/source/_templates/.placeholder
tiny_kubernetes/__init__.py
tiny_kubernetes/kubernetes.py
tiny_kubernetes.egg-info/PKG-INFO
tiny_kubernetes.egg-info/SOURCES.txt
tiny_kubernetes.egg-info/dependency_links.txt
tiny_kubernetes.egg-info/not-zip-safe
tiny_kubernetes.egg-info/pbr.json
tiny_kubernetes.egg-info/requires.txt
tiny_kubernetes.egg-info/top_level.txt
tiny_kubernetes/tests/__init__.py
tiny_kubernetes/tests/base.py
tiny_kubernetes/tests/test_tiny_kubernetes.py