Metadata-Version: 2.1
Name: tiny-kubernetes
Version: 1.1.1
Summary: A tiny Kubernetes client for Python
Home-page: http://github.com/monasca/tiny-kubernetes/
Author: Monasca team
Author-email: monasca@lists.launchpad.net
License: Apache-2
Platform: UNKNOWN
Classifier: Intended Audience :: Information Technology
Classifier: Intended Audience :: System Administrators
Classifier: License :: OSI Approved :: Apache Software License
Classifier: Operating System :: POSIX :: Linux
Classifier: Programming Language :: Python
Classifier: Programming Language :: Python :: 2
Classifier: Programming Language :: Python :: 2.7
Classifier: Programming Language :: Python :: 3
Classifier: Programming Language :: Python :: 3.3
Classifier: Programming Language :: Python :: 3.4
